demo/__init__.py
demo/aiohttp_server.py
demo/graphiql_template.py
graphql_ws/__init__.py
graphql_ws/_version_git.py
graphql_ws/abc.py
graphql_ws/aiohttp.py
graphql_ws/protocol.py
graphql_ws/server.py
graphql_ws/testing.py
graphql_ws_aiohttp-0.0.1.dist-info/LICENSE
graphql_ws_aiohttp-0.0.1.dist-info/METADATA
graphql_ws_aiohttp-0.0.1.dist-info/WHEEL
graphql_ws_aiohttp-0.0.1.dist-info/top_level.txt
graphql_ws_aiohttp-0.0.1.dist-info/RECORD
