Metadata-Version: 2.1
Name: graphql-ws-aiohttp
Version: 0.0.1
Summary: A GraphQL WebSocket server and client to facilitate GraphQL queries, mutations and subscriptions over WebSocket
Home-page: https://github.com/dls-controls/graphql-ws-aiohttp
Author: Callum Forrester, Devin Fee
Author-email: callum.forrester@diamond.ac.uk
License: Apache License 2.0
Platform: UNKNOWN
Classifier: Development Status :: 4 - Beta
Classifier: License :: OSI Approved :: Apache Software License
Classifier: Programming Language :: Python :: 3.7
Classifier: Programming Language :: Python :: 3.8
Classifier: Programming Language :: Python :: 3.9
Requires-Dist: aiohttp (>3.4)
Requires-Dist: graphql-core (>3.0)
Provides-Extra: dev
Requires-Dist: black (==19.10b0) ; extra == 'dev'
Requires-Dist: isort (>5.0) ; extra == 'dev'
Requires-Dist: pytest-cov ; extra == 'dev'
Requires-Dist: pytest-mypy ; extra == 'dev'
Requires-Dist: pytest-flake8 ; extra == 'dev'
Requires-Dist: pytest-black ; extra == 'dev'
Requires-Dist: pytest-asyncio ; extra == 'dev'
Requires-Dist: flake8-isort ; extra == 'dev'
Requires-Dist: sphinx-rtd-theme-github-versions ; extra == 'dev'
Provides-Extra: include_package_data
Requires-Dist: False ; extra == 'include_package_data'
